opynsense/__init__.py
opynsense/classes/interface.py
opynsense/classes/kea.py
opynsense/main.py
opynsense-0.1.3.dist-info/LICENSE
opynsense-0.1.3.dist-info/METADATA
opynsense-0.1.3.dist-info/WHEEL
opynsense-0.1.3.dist-info/RECORD
